project_aggregator/__init__.py
project_aggregator/logging_config.py
project_aggregator/logic.py
project_aggregator/main.py
project_aggregator-0.3.1.dist-info/entry_points.txt
project_aggregator-0.3.1.dist-info/LICENSE
project_aggregator-0.3.1.dist-info/METADATA
project_aggregator-0.3.1.dist-info/WHEEL
project_aggregator-0.3.1.dist-info/RECORD
