Metadata-Version: 2.3
Name: project-aggregator
Version: 0.3.1
Summary: 폴더 구조와 코드들을 하나의 txt 파일에 작성해주는 도구
License: MIT
Keywords: cli,code-aggregator,utility,project-structure
Author: 👻👽🤖🧙‍♂️🫠
Author-email: sprain6628@gmail.com
Requires-Python: >=3.13
Classifier: License :: OSI Approved :: MIT License
Classifier: Programming Language :: Python :: 3
Classifier: Programming Language :: Python :: 3.13
Requires-Dist: coloredlogs (>=15.0,<16.0.0)
Requires-Dist: pathspec (>=0.12.1,<0.13.0)
Requires-Dist: platformdirs (>=4.0.0,<5.0.0)
Requires-Dist: typer[all] (>=0.9.0,<1.0.0)
Project-URL: Homepage, https://github.com/authentic0376/project_aggregator
Project-URL: Repository, https://github.com/authentic0376/project_aggregator
